{
  "id": "CODE",
  "title": "CodEuphoria",
  "description": "A thrilling coding challenge designed to test problem-solving skills and programming proficiency. Participants will be given a set of coding problems and must implement efficient solutions within the given time. All programming languages are allowed, ensuring a level playing field for all participants.",
  "details": {
    "type": "TECHNICAL",
    "date": "17/02/2025",
    "min_team_size": 1,
    "max_team_size": 1,
    "time": "12PM-2.30PM",
    "thumb": "https://github.com/Magnuscit/events-data-25/blob/master/events/CODE/assets/1.png",
    "banner": "https://github.com/Magnuscit/events-data-25/blob/master/events/CODE/assets/2.png",
    "price": 0
  },
  "registration": [
    "Only college students are permitted to participate.",
    "A valid college ID is mandatory.",
    "Participants must wear the registration throughout the day.",
    "Prior registration is mandatory to attend any event/workshops, either online or on-spot.",
    "Re-entry is not allowed, and the fee paid for any event/workshops is non-refundable."
  ],
  "rules": [
    "Team Size: Individual participation.",
    "Event Duration: 2 hours (approx).",
    "Participants will be given a set number of coding problems to solve.",
    "Participants can bring their own laptop or use a provided PC.",
    "All programming languages are allowed.",
    "Additional instructions will be given at the start of the event.",
    "Any form of plagiarism will lead to immediate disqualification."
  ],
  "contacts": [
    { "incharge": "Saathvik", "phno": "9492045797" },
    { "incharge": "Faheem", "phno": "7305147636" }
  ]
}
